{
    "fixes": [
        {
            "name": "DUMSO",
            "lat": 22.391733333333335,
            "lon": 17.134441666666667
        },
        {
            "name": "ISAAC",
            "lat": 22.870022216666666,
            "lon": 17.123208333333334
        },
        {
            "name": "KAPPI",
            "lat": 22.321911116666666,
            "lon": 17.031825
        },
        {
            "name": "RW01M",
            "lat": 22.613888883333335,
            "lon": 17.080555566666668
        },
        {
            "name": "TEXET",
            "lat": 22.417319433333333,
            "lon": 16.956694433333332
        },
        {
            "name": "TILLY",
            "lat": 22.800155566666668,
            "lon": 17.020277783333334
        },
        {
            "name": "WE01F",
            "lat": 22.696388883333334,
            "lon": 17.094166666666666
        },
        {
            "name": "WE01I",
            "lat": 22.7875,
            "lon": 17.109444433333334
        },
        {
            "name": "WE19F",
            "lat": 22.495555566666667,
            "lon": 17.060833333333335
        },
        {
            "name": "WE19I",
            "lat": 22.40444443333333,
            "lon": 17.045555566666668
        },
        {
            "name": "WE19M",
            "lat": 22.578055566666666,
            "lon": 17.074444433333333
        },
        {
            "name": "WEM01",
            "lat": 22.531111116666665,
            "lon": 17.066666666666666
        },
        {
            "name": "WEM02",
            "lat": 22.721944433333334,
            "lon": 17.098333333333333
        }
    ],
    "rnws": [
        "RNW 01",
        "RNW 09",
        "RNW 19",
        "RNW 27"
    ],
    "sids": [],
    "stars": [],
    "approaches": [
        {
            "name": "RNAV01",
            "fixes": {
                "WE01I": "WE01I AT OR ABOVE 9000",
                "WE01F": "WE01F 7910",
                "RW01M": "OVERFLY RW01M 5625 RNW 01",
                "WEM01": "OVERFLY WEM01 TURN LEFT DIRECT",
                "TILLY": "TILLY AT OR ABOVE 10000 HOLD AT TILLY RIGHT TURN INBOUNDCOURSE 093 ALT 10000 LEGTIME 1 FAF WE01F MAP RNW 01M"
            },
            "transitions": [
                {
                    "name": "ISAAC",
                    "fixes": {
                        "ISAAC": "ISAAC"
                    }
                },
                {
                    "name": "TILLY",
                    "fixes": {
                        "TILLY": "TILLY"
                    }
                }
            ]
        },
        {
            "name": "RNAV19",
            "fixes": {
                "WE19I": "WE19I AT OR ABOVE 8500",
                "WE19F": "WE19F 7500",
                "WE19M": "OVERFLY WE19M 5911 RNW 19",
                "WEM02": "OVERFLY WEM02 TURN RIGHT DIRECT",
                "TEXET": "TEXET AT OR ABOVE 10000 HOLD AT TEXET LEFT TURN INBOUNDCOURSE 093 ALT 10000 LEGTIME 1 FAF WE19F MAP WE19M"
            },
            "transitions": [
                {
                    "name": "DUMSO",
                    "fixes": {
                        "DUMSO": "DUMSO"
                    }
                },
                {
                    "name": "KAPPI",
                    "fixes": {
                        "KAPPI": "KAPPI"
                    }
                },
                {
                    "name": "TEXET",
                    "fixes": {
                        "TEXET": "TEXET"
                    }
                }
            ]
        }
    ]
}