{
    "fixes": [
        {
            "name": "ANGIL",
            "lat": 47.96455556666667,
            "lon": 114.15791388333334
        },
        {
            "name": "ARLEE",
            "lat": 47.14095,
            "lon": 114.09975278333333
        },
        {
            "name": "BESKE",
            "lat": 47.613191666666665,
            "lon": 114.25355278333333
        },
        {
            "name": "CABLI",
            "lat": 47.41750556666667,
            "lon": 114.27805556666667
        },
        {
            "name": "DODSE",
            "lat": 47.54566943333333,
            "lon": 114.31100556666667
        },
        {
            "name": "EDOBE",
            "lat": 47.46666666666667,
            "lon": 114.93386388333333
        },
        {
            "name": "FABID",
            "lat": 47.500416666666666,
            "lon": 114.49108611666666
        },
        {
            "name": "FCA",
            "lat": 48.21410278333333,
            "lon": 114.17589166666667
        },
        {
            "name": "GORTE",
            "lat": 47.459011116666666,
            "lon": 114.38448611666666
        },
        {
            "name": "HALSO",
            "lat": 47.777672216666666,
            "lon": 114.144375
        },
        {
            "name": "ITONE",
            "lat": 47.972605566666665,
            "lon": 114.10217221666667
        },
        {
            "name": "JAGEL",
            "lat": 48.055566666666664,
            "lon": 114.09131666666667
        },
        {
            "name": "KULTE",
            "lat": 47.82326943333333,
            "lon": 114.12163056666667
        },
        {
            "name": "MIGSE",
            "lat": 47.677644433333334,
            "lon": 114.19854721666667
        },
        {
            "name": "POLAE",
            "lat": 47.464930566666666,
            "lon": 114.29925
        },
        {
            "name": "TEPSE",
            "lat": 47.777341666666665,
            "lon": 114.14454166666667
        }
    ],
    "rnws": [
        "RNW 18",
        "RNW 36"
    ],
    "sids": [
        {
            "name": "ANGIL1",
            "rnw": "36",
            "fixes": {
                "TEPSE": "TEPSE",
                "ANGIL": "ANGIL LEFT TURN INBOUNDCOURSE 340 ALT 10000 LEGDIST 7"
            },
            "sub_fixes": [],
            "transitions": []
        }
    ],
    "stars": [],
    "approaches": [
        {
            "name": "RNAV18",
            "fixes": {
                "ITONE": "ITONE AT OR ABOVE 7000",
                "KULTE": "KULTE 5500",
                "HALSO": "HALSO AT OR ABOVE 4560 RNW 18 TRK 182 UNTIL 3341",
                "POLAE": "OVERFLY POLAE AT OR ABOVE 9200 HOLD AT POLAE LEFT TURN INBOUNDCOURSE 002 LEGDIST 6 FAF KULTE MAP RNW 18"
            },
            "transitions": [
                {
                    "name": "FCA",
                    "fixes": {
                        "FCA": "FCA AT OR ABOVE 8000",
                        "JAGEL": "JAGEL AT OR ABOVE 8000"
                    }
                }
            ]
        },
        {
            "name": "RNAV36",
            "fixes": {
                "GORTE": "GORTE AT OR ABOVE 8100 GORTE AT OR ABOVE 9000 HOLD AT GORTE LEFT TURN INBOUNDCOURSE 028 LEGDIST 6 FAF DODSE MAP MIGSE",
                "DODSE": "DODSE 6400",
                "BESKE": "BESKE AT OR ABOVE 4800",
                "MIGSE": "MIGSE 3287 RNW 36 TRK 013 UNTIL 4500 TURN LEFT DIRECT"
            },
            "transitions": [
                {
                    "name": "ARLEE",
                    "fixes": {
                        "ARLEE": "ARLEE",
                        "CABLI": "CABLI AT OR ABOVE 8500"
                    }
                },
                {
                    "name": "EDOBE",
                    "fixes": {
                        "EDOBE": "EDOBE",
                        "FABID": "FABID AT OR ABOVE 8500"
                    }
                },
                {
                    "name": "GORTE",
                    "fixes": {
                        "GORTE": "GORTE LEFT TURN INBOUNDCOURSE 028 ALT 8100 LEGDIST 6"
                    }
                }
            ]
        }
    ]
}