{
    "fixes": [
        {
            "name": "CIVET",
            "lat": 34.035266666666665,
            "lon": 117.38993888333333
        },
        {
            "name": "DANNN",
            "lat": 33.69028888333333,
            "lon": 117.09788611666667
        },
        {
            "name": "DISEY",
            "lat": 33.64419443333333,
            "lon": 117.11003888333333
        },
        {
            "name": "ECULU",
            "lat": 33.726866666666666,
            "lon": 117.08823333333333
        },
        {
            "name": "GAREY",
            "lat": 34.166330566666666,
            "lon": 117.23223333333334
        },
        {
            "name": "JESEX",
            "lat": 33.8435,
            "lon": 117.24383888333334
        },
        {
            "name": "KELTE",
            "lat": 33.97683333333333,
            "lon": 117.04866111666666
        },
        {
            "name": "TANNR",
            "lat": 33.47663888333334,
            "lon": 117.16136943333333
        },
        {
            "name": "TIQMU",
            "lat": 33.81050556666667,
            "lon": 117.06612778333333
        }
    ],
    "rnws": [
        "RNW 18",
        "RNW 36"
    ],
    "sids": [],
    "stars": [],
    "approaches": [
        {
            "name": "RNAV18",
            "fixes": {
                "TIQMU": "TIQMU AT OR ABOVE 4600",
                "ECULU": "ECULU AT OR ABOVE 3800",
                "DANNN": "DANNN 3500",
                "DISEY": "DISEY AT OR ABOVE 2600 RNW 18 TRK 179 UNTIL 2500 TURN RIGHT DIRECT",
                "JESEX": "OVERFLY JESEX AT OR ABOVE 5000 HOLD AT JESEX LEFT TURN INBOUNDCOURSE 090 LEGDIST 5 FAF DANNN MAP RNW 18"
            },
            "transitions": [
                {
                    "name": "CIVET",
                    "fixes": {
                        "CIVET": "CIVET",
                        "JESEX": "JESEX AT OR ABOVE 6800"
                    }
                },
                {
                    "name": "GAREY",
                    "fixes": {
                        "GAREY": "GAREY",
                        "KELTE": "KELTE AT OR ABOVE 9000"
                    }
                },
                {
                    "name": "TANNR",
                    "fixes": {
                        "TANNR": "TANNR",
                        "TIQMU": "OVERFLY TIQMU AT OR ABOVE 4600 HOLD AT TIQMU RIGHT TURN INBOUNDCOURSE 179 ALT 4600 LEGDIST 5"
                    }
                }
            ]
        }
    ]
}