{
    "fixes": [
        {
            "name": "ASCHE",
            "lat": 32.695766666666664,
            "lon": 93.70616943333333
        },
        {
            "name": "AYEEE",
            "lat": 32.684441666666665,
            "lon": 93.80273888333333
        },
        {
            "name": "BABYE",
            "lat": 32.58653888333333,
            "lon": 93.95429443333333
        },
        {
            "name": "BEKEN",
            "lat": 32.40796111666667,
            "lon": 94.01794443333333
        },
        {
            "name": "BICYA",
            "lat": 32.36846666666667,
            "lon": 93.75829721666666
        },
        {
            "name": "CADOZ",
            "lat": 32.796405566666664,
            "lon": 94.14410278333334
        },
        {
            "name": "CFVRS",
            "lat": 32.31886943333333,
            "lon": 93.71385556666667
        },
        {
            "name": "COBAV",
            "lat": 32.288013883333335,
            "lon": 93.68630278333333
        },
        {
            "name": "DEEEH",
            "lat": 32.502780566666665,
            "lon": 94.11508333333333
        },
        {
            "name": "DOCKK",
            "lat": 32.35703888333333,
            "lon": 94.01893056666667
        },
        {
            "name": "DODDY",
            "lat": 32.40031943333334,
            "lon": 93.92756388333333
        },
        {
            "name": "EIC",
            "lat": 32.771363883333336,
            "lon": 93.80993056666667
        },
        {
            "name": "EMG",
            "lat": 32.40040556666667,
            "lon": 93.59514721666666
        },
        {
            "name": "EXITE",
            "lat": 32.012205566666665,
            "lon": 93.95116666666667
        },
        {
            "name": "FORBE",
            "lat": 32.372047216666665,
            "lon": 93.76148333333333
        },
        {
            "name": "GASSR",
            "lat": 32.41053611666667,
            "lon": 93.90596943333334
        },
        {
            "name": "GIGGS",
            "lat": 32.351475,
            "lon": 94.03066388333333
        },
        {
            "name": "HERMR",
            "lat": 32.63461388333333,
            "lon": 93.99766111666666
        },
        {
            "name": "JAVEE",
            "lat": 32.50355,
            "lon": 93.87955833333334
        },
        {
            "name": "JENNA",
            "lat": 32.42500278333333,
            "lon": 93.28652221666667
        },
        {
            "name": "KEEBK",
            "lat": 32.494669433333335,
            "lon": 93.727675
        },
        {
            "name": "LORIY",
            "lat": 32.52421666666667,
            "lon": 94.05192778333333
        },
        {
            "name": "MMIKE",
            "lat": 32.549763883333334,
            "lon": 93.61046666666667
        },
        {
            "name": "MOKPE",
            "lat": 32.16174443333333,
            "lon": 93.81449443333334
        },
        {
            "name": "NEVER",
            "lat": 32.63558333333334,
            "lon": 94.61959443333333
        },
        {
            "name": "ONGOO",
            "lat": 32.554966666666665,
            "lon": 93.92583611666667
        },
        {
            "name": "PICIS",
            "lat": 32.388919433333335,
            "lon": 93.52953611666666
        },
        {
            "name": "QEENB",
            "lat": 32.21121111666667,
            "lon": 93.9231
        },
        {
            "name": "SPOUT",
            "lat": 32.299655566666665,
            "lon": 94.51781388333333
        },
        {
            "name": "UNOTE",
            "lat": 32.47039443333333,
            "lon": 93.77920556666666
        },
        {
            "name": "WOXAT",
            "lat": 32.432491666666664,
            "lon": 93.85952221666666
        }
    ],
    "rnws": [
        "RNW 06",
        "RNW 14",
        "RNW 24",
        "RNW 32"
    ],
    "sids": [],
    "stars": [],
    "approaches": [
        {
            "name": "ILS14",
            "fixes": {
                "ONGOO": "ONGOO AT OR ABOVE 2600",
                "JAVEE": "JAVEE 1500 RNW 14 TRK 141 UNTIL 2000",
                "EMG": "EMG AT OR ABOVE 2000 HOLD AT EMG RIGHT TURN INBOUNDCOURSE 323 LEGTIME 1 FAF JAVEE MAP RNW 14"
            },
            "transitions": [
                {
                    "name": "CADOZ",
                    "fixes": {
                        "CADOZ": "CADOZ",
                        "HERMR": "HERMR AT OR ABOVE 3100"
                    }
                },
                {
                    "name": "EIC",
                    "fixes": {
                        "EIC": "EIC",
                        "HERMR": "HERMR AT OR ABOVE 3100"
                    }
                }
            ]
        },
        {
            "name": "ILS32",
            "fixes": {
                "CFVRS": "CFVRS AT OR ABOVE 1900",
                "FORBE": "FORBE 1817 RNW 32 TRK 321 UNTIL 800",
                "EIC": "EIC AT OR ABOVE 3100 HOLD AT EIC RIGHT TURN INBOUNDCOURSE 291 LEGTIME 1 FAF FORBE MAP RNW 32"
            },
            "transitions": [
                {
                    "name": "EIC",
                    "fixes": {
                        "EIC": "EIC",
                        "FORBE": "FORBE AT OR ABOVE 2100 HOLD AT FORBE LEFT TURN INBOUNDCOURSE 321 ALT 1900 LEGTIME 1"
                    }
                },
                {
                    "name": "EMG",
                    "fixes": {
                        "EMG": "EMG",
                        "FORBE": "FORBE AT OR ABOVE 1900 HOLD AT FORBE LEFT TURN INBOUNDCOURSE 321 ALT 1900 LEGTIME 1"
                    }
                }
            ]
        },
        {
            "name": "LOC06",
            "fixes": {
                "GIGGS": "GIGGS AT OR ABOVE 2000",
                "DODDY": "DODDY 2000",
                "WOXAT": "WOXAT AT OR ABOVE 740 RNW 06 TRK 059 UNTIL 700",
                "EMG": "EMG AT OR ABOVE 2000 HOLD AT EMG LEFT TURN INBOUNDCOURSE 120 LEGTIME 1 FAF DODDY MAP RNW 06"
            },
            "transitions": []
        },
        {
            "name": "RNAV06",
            "fixes": {
                "DOCKK": "DOCKK AT OR ABOVE 2100",
                "GASSR": "GASSR 1600 RNW 06 TRK 059 UNTIL 658",
                "MMIKE": "OVERFLY MMIKE AT OR ABOVE 3000 HOLD AT MMIKE RIGHT TURN INBOUNDCOURSE 239 LEGDIST 4 FAF GASSR MAP RNW 06"
            },
            "transitions": [
                {
                    "name": "DOCKK",
                    "fixes": {
                        "DOCKK": "DOCKK RIGHT TURN INBOUNDCOURSE 059 ALT 2100 LEGDIST 4"
                    }
                },
                {
                    "name": "EXITE",
                    "fixes": {
                        "EXITE": "EXITE",
                        "QEENB": "QEENB AT OR ABOVE 2100"
                    }
                },
                {
                    "name": "NEVER",
                    "fixes": {
                        "NEVER": "NEVER",
                        "DEEEH": "DEEEH AT OR ABOVE 2100"
                    }
                }
            ]
        },
        {
            "name": "RNAV14",
            "fixes": {
                "BABYE": "BABYE AT OR ABOVE 2500",
                "JAVEE": "JAVEE 1500 RNW 14 TRK 141 UNTIL 458",
                "COBAV": "OVERFLY COBAV AT OR ABOVE 3000 HOLD AT COBAV RIGHT TURN INBOUNDCOURSE 321 ALT 3000 LEGDIST 4 FAF JAVEE MAP RNW 14"
            },
            "transitions": [
                {
                    "name": "AYEEE",
                    "fixes": {
                        "AYEEE": "AYEEE"
                    }
                },
                {
                    "name": "BABYE",
                    "fixes": {
                        "BABYE": "BABYE RIGHT TURN INBOUNDCOURSE 136 ALT 2500 LEGDIST 4"
                    }
                },
                {
                    "name": "BEKEN",
                    "fixes": {
                        "BEKEN": "BEKEN",
                        "LORIY": "LORIY AT OR ABOVE 3000"
                    }
                },
                {
                    "name": "SPOUT",
                    "fixes": {
                        "SPOUT": "SPOUT",
                        "LORIY": "LORIY AT OR ABOVE 3000"
                    }
                }
            ]
        },
        {
            "name": "RNAV24",
            "fixes": {
                "MMIKE": "MMIKE AT OR ABOVE 2000",
                "KEEBK": "KEEBK 1900",
                "UNOTE": "UNOTE AT OR ABOVE 940 RNW 24 TRK 239 UNTIL 487",
                "DOCKK": "OVERFLY DOCKK AT OR ABOVE 3000 HOLD AT DOCKK RIGHT TURN INBOUNDCOURSE 059 ALT 3000 LEGDIST 4 FAF KEEBK MAP RNW 24"
            },
            "transitions": [
                {
                    "name": "EIC",
                    "fixes": {
                        "EIC": "EIC",
                        "ASCHE": "ASCHE AT OR ABOVE 3000"
                    }
                },
                {
                    "name": "MMIKE",
                    "fixes": {
                        "MMIKE": "MMIKE RIGHT TURN INBOUNDCOURSE 239 ALT 2000 LEGDIST 4"
                    }
                }
            ]
        },
        {
            "name": "RNAV32",
            "fixes": {
                "COBAV": "COBAV AT OR ABOVE 2400",
                "BICYA": "BICYA 1900 RNW 32 TRK 321 UNTIL 422",
                "BABYE": "OVERFLY BABYE AT OR ABOVE 2600 HOLD AT BABYE RIGHT TURN INBOUNDCOURSE 136 LEGDIST 4 FAF BICYA MAP RNW 32"
            },
            "transitions": [
                {
                    "name": "COBAV",
                    "fixes": {
                        "COBAV": "COBAV RIGHT TURN INBOUNDCOURSE 321 ALT 2400 LEGDIST 4"
                    }
                },
                {
                    "name": "JENNA",
                    "fixes": {
                        "JENNA": "JENNA",
                        "PICIS": "PICIS AT OR ABOVE 3000"
                    }
                },
                {
                    "name": "MOKPE",
                    "fixes": {
                        "MOKPE": "MOKPE"
                    }
                }
            ]
        }
    ]
}