{
    "fixes": [
        {
            "name": "AF001",
            "lat": 17.000790433333332,
            "lon": 89.78950998333333
        },
        {
            "name": "AF002",
            "lat": 17.025610416666666,
            "lon": 89.82689743333333
        },
        {
            "name": "AF003",
            "lat": 17.035591666666665,
            "lon": 89.87120253333333
        },
        {
            "name": "AF004",
            "lat": 17.029342766666666,
            "lon": 89.91624966666667
        },
        {
            "name": "AF005",
            "lat": 17.007734866666667,
            "lon": 89.9557592
        },
        {
            "name": "AF006",
            "lat": 17.024331016666668,
            "lon": 89.82399698333333
        },
        {
            "name": "AF007",
            "lat": 17.034566683333335,
            "lon": 89.85954311666667
        },
        {
            "name": "AF008",
            "lat": 17.034101783333334,
            "lon": 89.89666403333334
        },
        {
            "name": "AF009",
            "lat": 17.022979416666665,
            "lon": 89.93191741666666
        },
        {
            "name": "AF010",
            "lat": 17.002230883333333,
            "lon": 89.96203508333333
        },
        {
            "name": "AF011",
            "lat": 17.02320965,
            "lon": 89.9314426
        },
        {
            "name": "AF012",
            "lat": 17.010326366666668,
            "lon": 89.95247431666667
        },
        {
            "name": "AF013",
            "lat": 16.993615933333334,
            "lon": 89.97031846666667
        },
        {
            "name": "AF014",
            "lat": 16.823456516666667,
            "lon": 89.94643426666667
        },
        {
            "name": "AF015",
            "lat": 16.853772133333333,
            "lon": 89.97758686666667
        },
        {
            "name": "AF016",
            "lat": 16.892757533333334,
            "lon": 89.99532781666667
        },
        {
            "name": "ALIGO",
            "lat": 17.08,
            "lon": 89.47527778333334
        },
        {
            "name": "AMARU",
            "lat": 17.226388883333332,
            "lon": 89.58138888333333
        },
        {
            "name": "BATUN",
            "lat": 16.944472216666668,
            "lon": 89.94977778333333
        },
        {
            "name": "CF11",
            "lat": 16.951291666666666,
            "lon": 89.99352221666666
        },
        {
            "name": "CI11",
            "lat": 16.953544433333334,
            "lon": 89.97448888333334
        },
        {
            "name": "CI11W",
            "lat": 16.959525,
            "lon": 89.99078056666667
        },
        {
            "name": "CI11X",
            "lat": 16.977391666666666,
            "lon": 90.03948611666667
        },
        {
            "name": "CS11",
            "lat": 16.946686116666665,
            "lon": 89.97680556666667
        },
        {
            "name": "D043J",
            "lat": 17.042025,
            "lon": 89.75859166666666
        },
        {
            "name": "D067J",
            "lat": 16.983527783333333,
            "lon": 89.71608056666666
        },
        {
            "name": "D067O",
            "lat": 17.015727783333332,
            "lon": 89.63581388333333
        },
        {
            "name": "D194J",
            "lat": 16.757569433333334,
            "lon": 89.92218888333333
        },
        {
            "name": "D194O",
            "lat": 16.676827783333334,
            "lon": 89.94498888333334
        },
        {
            "name": "D278G",
            "lat": 16.935302783333334,
            "lon": 89.99704166666666
        },
        {
            "name": "D279J",
            "lat": 16.945141666666668,
            "lon": 90.04825278333334
        },
        {
            "name": "D298G",
            "lat": 16.974002783333333,
            "lon": 89.98400278333334
        },
        {
            "name": "D345J",
            "lat": 17.081080566666667,
            "lon": 89.91996666666667
        },
        {
            "name": "DEROS",
            "lat": 16.884005566666666,
            "lon": 89.76040833333333
        },
        {
            "name": "EMEMA",
            "lat": 17.324166666666667,
            "lon": 89.98527778333333
        },
        {
            "name": "JAGUA",
            "lat": 16.6107,
            "lon": 90.08536111666666
        },
        {
            "name": "MA11",
            "lat": 16.923186116666667,
            "lon": 89.89156388333333
        },
        {
            "name": "MADEL",
            "lat": 16.503444433333332,
            "lon": 89.82655556666667
        },
        {
            "name": "SERLA",
            "lat": 15.702777783333334,
            "lon": 90.21861111666666
        },
        {
            "name": "TADIN",
            "lat": 16.025833333333335,
            "lon": 90.12777778333333
        },
        {
            "name": "TIK",
            "lat": 16.919036116666668,
            "lon": 89.876525
        },
        {
            "name": "TUCAN",
            "lat": 16.51527778333333,
            "lon": 89.99055556666667
        },
        {
            "name": "ULENA",
            "lat": 16.939777783333334,
            "lon": 89.95173333333334
        }
    ],
    "rnws": [
        "RNW 11",
        "RNW 29"
    ],
    "sids": [
        {
            "name": "ACTUN",
            "rnw": "11",
            "fixes": {
                "DEROS": "OVERFLY DEROS",
                "MADEL": "MADEL AT OR ABOVE 5000",
                "SERLA": "SERLA"
            },
            "sub_fixes": [],
            "transitions": []
        }
    ],
    "stars": [],
    "approaches": [
        {
            "name": "VORDX11",
            "fixes": {
                "CF11": "CF11 AT OR ABOVE 2500",
                "ULENA": "ULENA 1840",
                "MA11": "MA11 692 RNW 11 TRK 106 UNTIL 2500 TURN LEFT DIRECT",
                "TIK": "TIK AT OR ABOVE 3000 FAF ULENA MAP MA11"
            },
            "transitions": [
                {
                    "name": "ALIGO",
                    "fixes": {
                        "ALIGO": "ALIGO",
                        "D067O": "D067O AT OR ABOVE 4000",
                        "D067J": "D067J"
                    }
                },
                {
                    "name": "AMARU",
                    "fixes": {
                        "AMARU": "AMARU",
                        "D043J": "D043J AT OR ABOVE 4000"
                    }
                },
                {
                    "name": "EMEMA",
                    "fixes": {
                        "EMEMA": "EMEMA",
                        "D345J": "D345J AT OR ABOVE 4000"
                    }
                },
                {
                    "name": "TUCAN",
                    "fixes": {
                        "TUCAN": "TUCAN",
                        "D194O": "D194O AT OR ABOVE 4000",
                        "D194J": "D194J AT OR ABOVE 4000"
                    }
                }
            ]
        },
        {
            "name": "VORDY11",
            "fixes": {
                "CS11": "CS11 AT OR ABOVE 2500",
                "ULENA": "ULENA 1840",
                "MA11": "MA11 692 RNW 11 TRK 106 UNTIL 2500 TURN LEFT DIRECT",
                "TIK": "TIK AT OR ABOVE 3000 FAF ULENA MAP MA11"
            },
            "transitions": [
                {
                    "name": "TIK",
                    "fixes": {
                        "TIK": "TIK AT OR ABOVE 3000 TRK 263 UNTIL 6.0 FROM TIK"
                    }
                }
            ]
        },
        {
            "name": "VORDZ11",
            "fixes": {
                "CS11": "CS11 AT OR ABOVE 2500",
                "ULENA": "ULENA 1840",
                "MA11": "MA11 692 RNW 11 TRK 106 UNTIL 2500 TURN LEFT DIRECT",
                "TIK": "TIK AT OR ABOVE 3000 FAF ULENA MAP MA11"
            },
            "transitions": [
                {
                    "name": "TIK",
                    "fixes": {
                        "TIK": "TIK AT OR ABOVE 3000 TRK 309 UNTIL 6.0 FROM TIK"
                    }
                }
            ]
        },
        {
            "name": "ILSW11",
            "fixes": {
                "CI11W": "CI11W AT OR ABOVE 2500",
                "BATUN": "BATUN 1840 RNW 11 TRK 111 UNTIL 830 TRK 106 UNTIL 2500 TURN LEFT DIRECT",
                "TIK": "TIK AT OR ABOVE 3000 FAF BATUN MAP RNW 11"
            },
            "transitions": [
                {
                    "name": "ALIGO",
                    "fixes": {
                        "ALIGO": "ALIGO",
                        "D067O": "D067O AT OR ABOVE 4000",
                        "D067J": "D067J",
                        "AF001": "AF001",
                        "AF002": "AF002",
                        "AF003": "AF003",
                        "AF004": "AF004",
                        "AF005": "AF005",
                        "D298G": "D298G AT OR ABOVE 2500"
                    }
                },
                {
                    "name": "AMARU",
                    "fixes": {
                        "AMARU": "AMARU",
                        "D043J": "D043J AT OR ABOVE 4000",
                        "AF006": "AF006",
                        "AF007": "AF007",
                        "AF008": "AF008",
                        "AF009": "AF009",
                        "AF010": "AF010",
                        "D298G": "D298G AT OR ABOVE 2500"
                    }
                },
                {
                    "name": "EMEMA",
                    "fixes": {
                        "EMEMA": "EMEMA",
                        "D345J": "D345J AT OR ABOVE 4000",
                        "AF011": "AF011",
                        "AF012": "AF012",
                        "AF013": "AF013",
                        "D298G": "D298G AT OR ABOVE 2500"
                    }
                },
                {
                    "name": "TUCAN",
                    "fixes": {
                        "TUCAN": "TUCAN",
                        "D194O": "D194O AT OR ABOVE 4000",
                        "D194J": "D194J AT OR ABOVE 4000",
                        "AF014": "AF014",
                        "AF015": "AF015",
                        "AF016": "AF016",
                        "D278G": "D278G AT OR ABOVE 2500"
                    }
                }
            ]
        },
        {
            "name": "ILSX11",
            "fixes": {
                "CI11X": "CI11X AT OR ABOVE 3000",
                "BATUN": "BATUN 1840 RNW 11 TRK 111 UNTIL 830 TRK 106 UNTIL 2500 TURN LEFT DIRECT",
                "TIK": "TIK AT OR ABOVE 3000 FAF BATUN MAP RNW 11"
            },
            "transitions": [
                {
                    "name": "TADIN",
                    "fixes": {
                        "TADIN": "TADIN",
                        "JAGUA": "JAGUA AT OR ABOVE 5000",
                        "D279J": "D279J AT OR ABOVE 3000"
                    }
                }
            ]
        },
        {
            "name": "ILSY11",
            "fixes": {
                "CI11": "CI11 AT OR ABOVE 2500",
                "BATUN": "BATUN 1840 RNW 11 TRK 111 UNTIL 830 TRK 106 UNTIL 2500 TURN LEFT DIRECT",
                "TIK": "TIK AT OR ABOVE 3000 FAF BATUN MAP RNW 11"
            },
            "transitions": [
                {
                    "name": "TIK",
                    "fixes": {
                        "TIK": "TIK AT OR ABOVE 3000 TRK 268 UNTIL 6.0 FROM TIK"
                    }
                }
            ]
        },
        {
            "name": "ILSZ11",
            "fixes": {
                "CI11": "CI11 AT OR ABOVE 2500",
                "BATUN": "BATUN 1840 RNW 11 TRK 111 UNTIL 830 TRK 106 UNTIL 2500 TURN LEFT DIRECT",
                "TIK": "TIK AT OR ABOVE 3000 FAF BATUN MAP RNW 11"
            },
            "transitions": [
                {
                    "name": "TIK",
                    "fixes": {
                        "TIK": "TIK AT OR ABOVE 3000 TRK 315 UNTIL 6.0 FROM TIK"
                    }
                }
            ]
        }
    ]
}